<?xml version = '1.0' encoding = 'UTF-8'?>
<Diagram class="oracle.dbtools.crest.swingui.logical.DPVLogical" name="Logical" id="341D552B-85AE-5B50-CDDF-D26B75C982B2">
<createdBy>Administrator</createdBy>
<modifiedBy>Administrator</modifiedBy>
<createdTime>2024-01-13 14:08:33 UTC</createdTime>
<autoRoute>false</autoRoute>
<boxInbox>true</boxInbox>
<showLegend>false</showLegend>
<showLabels>false</showLabels>
<showRelAttributes>false</showRelAttributes>
<gridEnabled>false</gridEnabled>
<showGrid>false</showGrid>
<diagramColor>-1</diagramColor>
<display>false</display>
<notation>2</notation>
<objectViews>
<OView class="oracle.dbtools.crest.swingui.logical.TVEntity" oid="4DAA8D26-07A7-7648-553A-71FEBD145BD9" otype="Entity" vid="682F57FB-5981-8FA9-A844-DBB6A60CB576">
<hideElementsInCurrentOnly>false</hideElementsInCurrentOnly>
<bounds x="1025" y="130" width="189" height="83"/>
</OView>
<OView class="oracle.dbtools.crest.swingui.logical.TVEntity" oid="5D613B85-1A37-5646-058F-C5D0C995D8F9" otype="Entity" vid="9C77B535-0870-6B15-0F4A-AFAC4691B2A4">
<hideElementsInCurrentOnly>false</hideElementsInCurrentOnly>
<bounds x="293" y="605" width="192" height="145"/>
</OView>
<OView class="oracle.dbtools.crest.swingui.logical.TVEntity" oid="6C57B78E-1727-1CF4-34C3-4A5CBCF0F7AB" otype="Entity" vid="E096CF8E-AD62-3D10-4471-77F6A8131812">
<hideElementsInCurrentOnly>false</hideElementsInCurrentOnly>
<bounds x="45" y="625" width="187" height="113"/>
</OView>
<OView class="oracle.dbtools.crest.swingui.logical.TVEntity" oid="8321E01C-AA6C-43D7-517E-1A25A7CE708B" otype="Entity" vid="57175CBC-1641-1F60-0051-419B57CE5666">
<hideElementsInCurrentOnly>false</hideElementsInCurrentOnly>
<bounds x="542" y="608" width="184" height="101"/>
</OView>
<OView class="oracle.dbtools.crest.swingui.logical.TVEntity" oid="8FAE6508-0D6E-BE3B-2D21-3DF83D0F45AC" otype="Entity" vid="70E4D754-0D18-83A3-FD75-6B766522C0AF">
<hideElementsInCurrentOnly>false</hideElementsInCurrentOnly>
<bounds x="824" y="130" width="201" height="83"/>
</OView>
<OView class="oracle.dbtools.crest.swingui.logical.TVEntity" oid="9873D42C-3E53-AC41-9B39-D56BFDCC6FE5" otype="Entity" vid="FB513956-A983-01A6-01E6-C6CBE890B221">
<hideElementsInCurrentOnly>false</hideElementsInCurrentOnly>
<bounds x="956" y="560" width="166" height="184"/>
</OView>
<OView class="oracle.dbtools.crest.swingui.logical.TVEntity" oid="B16FF0D1-699F-A282-1237-0D9A2C0A3AA4" otype="Entity" vid="36B3D5B2-00CD-85E0-C4AD-F69440D1B9AF">
<hideElementsInCurrentOnly>false</hideElementsInCurrentOnly>
<bounds x="514" y="344" width="160" height="146"/>
</OView>
<OView class="oracle.dbtools.crest.swingui.logical.TVEntity" oid="C32D4C65-5596-1B45-1917-9E5194B63CE4" otype="Entity" vid="AC689B21-E90C-E698-614B-ADC4F9AC7425">
<hideElementsInCurrentOnly>false</hideElementsInCurrentOnly>
<bounds x="140" y="345" width="203" height="164"/>
</OView>
<OView class="oracle.dbtools.crest.swingui.logical.TVEntity" oid="C7BF2A9E-C995-228C-12BC-53A93764BC92" otype="Entity" vid="396FC4B5-55E3-75A1-D500-C93DEC5518A6">
<hideElementsInCurrentOnly>false</hideElementsInCurrentOnly>
<bounds x="516" y="5" width="164" height="141"/>
</OView>
<OView class="oracle.dbtools.crest.swingui.logical.TVEntity" oid="CB5E7CC3-E68D-0FD3-B1E1-6BC3717C67DA" otype="Entity" vid="3857A7CC-2B29-B692-7A64-6C65F831435E">
<hideElementsInCurrentOnly>false</hideElementsInCurrentOnly>
<bounds x="814" y="345" width="189" height="161"/>
</OView>
<OView class="oracle.dbtools.crest.swingui.logical.TVEntity" oid="F09942D0-072D-3FAD-92FF-BC5ACC0C0083" otype="Entity" vid="44B241FF-F638-47C9-749C-5753D00FA443">
<hideElementsInCurrentOnly>false</hideElementsInCurrentOnly>
<bounds x="814" y="0" width="410" height="223"/>
</OView>
</objectViews>
<connectors>
<Connector class="oracle.dbtools.crest.swingui.logical.TVRelation" oid="097611BF-1AEE-6E93-7EEA-EFEFB12ACA44" otype="Relation" vid_source="396FC4B5-55E3-75A1-D500-C93DEC5518A6" vid_target="36B3D5B2-00CD-85E0-C4AD-F69440D1B9AF">
<hideElementsInCurrentOnly>false</hideElementsInCurrentOnly>
<backgroundColor>-16777216</backgroundColor>
<lineWidth>1</lineWidth>
<points>
<point x="595" y="146"/>
<point x="595" y="344"/>
</points>
</Connector>
<Connector class="oracle.dbtools.crest.swingui.logical.TVRelation" oid="2141A881-5C69-C1F1-739B-D92928CAC610" otype="Relation" vid_source="57175CBC-1641-1F60-0051-419B57CE5666" vid_target="FB513956-A983-01A6-01E6-C6CBE890B221">
<hideElementsInCurrentOnly>false</hideElementsInCurrentOnly>
<backgroundColor>-16777216</backgroundColor>
<lineWidth>1</lineWidth>
<points>
<point x="726" y="658"/>
<point x="956" y="658"/>
</points>
</Connector>
<Connector class="oracle.dbtools.crest.swingui.logical.TVInheritanceRelation" oid="3B739F3A-9C86-714F-52A4-8334A4E7CC3A" otype="Hierarchy relation" vid_source="44B241FF-F638-47C9-749C-5753D00FA443" vid_target="70E4D754-0D18-83A3-FD75-6B766522C0AF">
<hideElementsInCurrentOnly>false</hideElementsInCurrentOnly>
<backgroundColor>-65536</backgroundColor>
<lineWidth>1</lineWidth>
</Connector>
<Connector class="oracle.dbtools.crest.swingui.logical.TVRelation" oid="5D55C2A0-1D26-F04F-7181-2D934B8A37C9" otype="Relation" vid_source="AC689B21-E90C-E698-614B-ADC4F9AC7425" vid_target="36B3D5B2-00CD-85E0-C4AD-F69440D1B9AF">
<hideElementsInCurrentOnly>false</hideElementsInCurrentOnly>
<backgroundColor>-16777216</backgroundColor>
<lineWidth>1</lineWidth>
<points>
<point x="343" y="417"/>
<point x="514" y="417"/>
</points>
</Connector>
<Connector class="oracle.dbtools.crest.swingui.logical.TVRelation" oid="818E2E76-FC70-3B23-F4A0-F504C22D677D" otype="Relation" vid_source="57175CBC-1641-1F60-0051-419B57CE5666" vid_target="3857A7CC-2B29-B692-7A64-6C65F831435E">
<hideElementsInCurrentOnly>false</hideElementsInCurrentOnly>
<backgroundColor>-16777216</backgroundColor>
<lineWidth>1</lineWidth>
<points>
<point x="693" y="608"/>
<point x="814" y="505"/>
</points>
</Connector>
<Connector class="oracle.dbtools.crest.swingui.logical.TVRelation" oid="85ABF50E-195A-6EE7-98A4-E877D6D58BFB" otype="Relation" vid_source="57175CBC-1641-1F60-0051-419B57CE5666" vid_target="36B3D5B2-00CD-85E0-C4AD-F69440D1B9AF">
<hideElementsInCurrentOnly>false</hideElementsInCurrentOnly>
<backgroundColor>-16777216</backgroundColor>
<lineWidth>1</lineWidth>
<points>
<point x="623" y="608"/>
<point x="623" y="490"/>
</points>
</Connector>
<Connector class="oracle.dbtools.crest.swingui.logical.TVRelation" oid="AA6B78CC-CABB-711C-6AAC-ACC258321F55" otype="Relation" vid_source="36B3D5B2-00CD-85E0-C4AD-F69440D1B9AF" vid_target="44B241FF-F638-47C9-749C-5753D00FA443">
<hideElementsInCurrentOnly>false</hideElementsInCurrentOnly>
<backgroundColor>-16777216</backgroundColor>
<lineWidth>1</lineWidth>
<points>
<point x="674" y="359"/>
<point x="863" y="223"/>
</points>
</Connector>
<Connector class="oracle.dbtools.crest.swingui.logical.TVRelation" oid="BACBDC51-302D-14F4-E847-B0FF8FC68301" otype="Relation" vid_source="36B3D5B2-00CD-85E0-C4AD-F69440D1B9AF" vid_target="36B3D5B2-00CD-85E0-C4AD-F69440D1B9AF">
<hideElementsInCurrentOnly>false</hideElementsInCurrentOnly>
<backgroundColor>-16777216</backgroundColor>
<lineWidth>1</lineWidth>
<points>
<point x="674" y="429"/>
<point x="699" y="429"/>
<point x="699" y="515"/>
<point x="608" y="515"/>
<point x="608" y="490"/>
</points>
</Connector>
<Connector class="oracle.dbtools.crest.swingui.logical.TVRelation" oid="CC7C1EA2-BB37-5787-A503-2F015EE71094" otype="Relation" vid_source="44B241FF-F638-47C9-749C-5753D00FA443" vid_target="FB513956-A983-01A6-01E6-C6CBE890B221">
<hideElementsInCurrentOnly>false</hideElementsInCurrentOnly>
<backgroundColor>-16777216</backgroundColor>
<lineWidth>1</lineWidth>
<points>
<point x="1039" y="223"/>
<point x="1039" y="560"/>
</points>
</Connector>
<Connector class="oracle.dbtools.crest.swingui.logical.TVRelation" oid="D795AFD2-C227-291F-E314-25A4DF47D083" otype="Relation" vid_source="AC689B21-E90C-E698-614B-ADC4F9AC7425" vid_target="9C77B535-0870-6B15-0F4A-AFAC4691B2A4">
<hideElementsInCurrentOnly>false</hideElementsInCurrentOnly>
<backgroundColor>-16777216</backgroundColor>
<lineWidth>1</lineWidth>
<points>
<point x="318" y="509"/>
<point x="318" y="605"/>
</points>
</Connector>
<Connector class="oracle.dbtools.crest.swingui.logical.TVRelation" oid="DA35CCD1-BA43-7F4C-35F2-1A0745ABEA55" otype="Relation" vid_source="396FC4B5-55E3-75A1-D500-C93DEC5518A6" vid_target="44B241FF-F638-47C9-749C-5753D00FA443">
<hideElementsInCurrentOnly>false</hideElementsInCurrentOnly>
<backgroundColor>-16777216</backgroundColor>
<lineWidth>1</lineWidth>
<points>
<point x="680" y="75"/>
<point x="814" y="75"/>
</points>
</Connector>
<Connector class="oracle.dbtools.crest.swingui.logical.TVRelation" oid="E73A86E1-D447-FB4A-A3D2-490F3D36AF10" otype="Relation" vid_source="AC689B21-E90C-E698-614B-ADC4F9AC7425" vid_target="E096CF8E-AD62-3D10-4471-77F6A8131812">
<hideElementsInCurrentOnly>false</hideElementsInCurrentOnly>
<backgroundColor>-16777216</backgroundColor>
<lineWidth>1</lineWidth>
<points>
<point x="186" y="509"/>
<point x="186" y="625"/>
</points>
</Connector>
<Connector class="oracle.dbtools.crest.swingui.logical.TVInheritanceRelation" oid="E88E805A-8D3B-C025-8524-A9C33AD83398" otype="Hierarchy relation" vid_source="44B241FF-F638-47C9-749C-5753D00FA443" vid_target="682F57FB-5981-8FA9-A844-DBB6A60CB576">
<hideElementsInCurrentOnly>false</hideElementsInCurrentOnly>
<backgroundColor>-65536</backgroundColor>
<lineWidth>1</lineWidth>
</Connector>
</connectors>
</Diagram>